ITS_CLI/__init__.py
ITS_CLI/api.py
ITS_CLI/client.py
ITS_CLI/config.py
ITS_CLI/logger.py
ITS_CLI/tcp_client.py
ITS_CLI/timeseriesdb.py
its_cli-0.9.7.dist-info/licenses/LICENSE
its_cli-0.9.7.dist-info/METADATA
its_cli-0.9.7.dist-info/WHEEL
its_cli-0.9.7.dist-info/top_level.txt
its_cli-0.9.7.dist-info/RECORD
