Metadata-Version: 2.4
Name: ITS_CLI
Version: 0.9.7
Summary: SMARTC&S Co., Ltd is a Korean company that produces and supplies various sensor equipment and provides the ITS (IoT Total Solution) service, which allows real-time monitoring and data analysis of sensor equipment data. The ITS_CLI provides a Python API that allows ITS users to directly access ITS data.
Home-page: https://github.com/bkchae/ITS_CLI
Author: SMARTC&S Co.,Ltd
Author-email: byungkwan.chae1@smartcs.co.kr
Classifier: Programming Language :: Python :: 3
Classifier: License :: OSI Approved :: MIT License
Classifier: Operating System :: OS Independent
Requires-Python: >=3.6
License-File: LICENSE
Requires-Dist: pandas
Requires-Dist: matplotlib
Requires-Dist: pyfiglet
Requires-Dist: tabulate
Requires-Dist: prettytable
Requires-Dist: scipy
Requires-Dist: influxdb_client
Dynamic: author
Dynamic: author-email
Dynamic: classifier
Dynamic: description
Dynamic: description-content-type
Dynamic: home-page
Dynamic: license-file
Dynamic: requires-dist
Dynamic: requires-python
Dynamic: summary
